ecc.cpython-38-x86_64-linux-gnu.so
epipolar_consistency-0.0.2.dist-info/LICENSE
epipolar_consistency-0.0.2.dist-info/METADATA
epipolar_consistency-0.0.2.dist-info/WHEEL
epipolar_consistency-0.0.2.dist-info/top_level.txt
epipolar_consistency-0.0.2.dist-info/RECORD
