Metadata-Version: 2.1
Name: epipolar-consistency
Version: 0.0.2
Summary: Python bindings for evaluating epipolar consistency conditions in transmission imaging.
License-File: LICENSE
